quickutil/__init__.py
quickutil/qos/__init__.py
quickutil/qos/qdir/__init__.py
quickutil/qtime/__init__.py
quickutil-0.0.1.dist-info/LICENSE
quickutil-0.0.1.dist-info/METADATA
quickutil-0.0.1.dist-info/WHEEL
quickutil-0.0.1.dist-info/top_level.txt
quickutil-0.0.1.dist-info/RECORD
