Metadata-Version: 2.1
Name: quickutil
Version: 0.0.1
Home-page: https://github.com/roninmaster21/quickutil
Author: roninmaster21
Author-email: 
License: MIT
Project-URL: Bug Tracker, https://github.com/roninmaster21/quickutil/issues
License-File: LICENSE
